base_loom_server/__init__.py
base_loom_server/app_runner.py
base_loom_server/base_loom_server.py
base_loom_server/base_mock_loom.py
base_loom_server/check_translation_files.py
base_loom_server/client_replies.py
base_loom_server/constants.py
base_loom_server/display.css
base_loom_server/display.html
base_loom_server/display.js
base_loom_server/enums.py
base_loom_server/example_loom_server.py
base_loom_server/example_mock_loom.py
base_loom_server/favicon-32x32.png
base_loom_server/main.py
base_loom_server/mock_streams.py
base_loom_server/nmcli_wifi.py
base_loom_server/pattern_database.py
base_loom_server/py.typed
base_loom_server/reduced_pattern.py
base_loom_server/rename_crowdin_files.py
base_loom_server/testutils.py
base_loom_server/translations.py
base_loom_server/utils.py
base_loom_server/version.py
base_loom_server/locales/Dansk.json
base_loom_server/locales/Deutsch.json
base_loom_server/locales/English.json
base_loom_server/locales/Español.json
base_loom_server/locales/Français.json
base_loom_server/locales/Italiano.json
base_loom_server/locales/Nederlands.json
base_loom_server/locales/Norsk.json
base_loom_server/locales/Suomi.json
base_loom_server/locales/Svenska.json
base_loom_server/locales/default.json
base_loom_server/test_data/pattern_files/eighteen shaft liftplan.wif
base_loom_server/test_data/pattern_files/many color liftplan and zeros.dtx
base_loom_server/test_data/pattern_files/many color liftplan and zeros.wif
base_loom_server/test_data/pattern_files/many color multiple treadles and zeros.dtx
base_loom_server/test_data/pattern_files/many color multiple treadles and zeros.wif
base_loom_server/test_data/pattern_files/many color multiple treadles and zeros.wpo
base_loom_server/test_data/pattern_files/many color single treadles.dtx
base_loom_server/test_data/pattern_files/many color single treadles.wif
base_loom_server/test_data/pattern_files/many color single treadles.wpo
base_loom_server/test_data/pattern_files/two color liftplan.dtx
base_loom_server-1.1.1.dist-info/licenses/LICENSE.txt
base_loom_server-1.1.1.dist-info/METADATA
base_loom_server-1.1.1.dist-info/WHEEL
base_loom_server-1.1.1.dist-info/entry_points.txt
base_loom_server-1.1.1.dist-info/top_level.txt
base_loom_server-1.1.1.dist-info/RECORD
