Metadata-Version: 2.4
Name: base_loom_server
Version: 1.1.1
Summary: Base package for web servers that control dobby multi-shaft looms
Author-email: Russell Owen <r3owen@gmail.com>
Project-URL: Homepage, https://pypi.org/project/base-loom-server/
Project-URL: Documentation, https://r-owen.github.io/base_loom_server/
Project-URL: Source, https://github.com/r-owen/base_loom_server
Project-URL: Issues, https://github.com/r-owen/base_loom_server/issues
Classifier: Programming Language :: Python :: 3
Classifier: License :: OSI Approved :: MIT License
Classifier: Operating System :: OS Independent
Requires-Python: >=3.11
License-File: LICENSE.txt
Requires-Dist: aiosqlite>=0.21
Requires-Dist: dtx_to_wif~=4.4
Requires-Dist: fastapi[standard]~=0.120
Requires-Dist: pyserial-asyncio-fast~=0.16
Provides-Extra: dev
Requires-Dist: mkapi; extra == "dev"
Requires-Dist: mkdocs-glightbox; extra == "dev"
Requires-Dist: mkdocs; extra == "dev"
Requires-Dist: pre-commit~=4.0; extra == "dev"
Requires-Dist: pytest~=8.3; extra == "dev"
Requires-Dist: pytest-asyncio~=0.25; extra == "dev"
Requires-Dist: sphinx; extra == "dev"
Requires-Dist: sphinxcontrib-napoleon; extra == "dev"
Dynamic: license-file
